altoshift/__init__.py
altoshift/mysql.py
altoshift/tools.py
altoshift-0.1.29.dist-info/LICENSE.md
altoshift-0.1.29.dist-info/METADATA
altoshift-0.1.29.dist-info/WHEEL
altoshift-0.1.29.dist-info/top_level.txt
altoshift-0.1.29.dist-info/RECORD
