Metadata-Version: 2.1
Name: altoshift
Version: 0.1.29
Summary: learning today make you better tomorrow
Home-page: https://altoshift.com
Author: eko
Author-email: eko@altoshift.com
License: MIT
Platform: UNKNOWN
Requires: requests(>=1.2.3)
Requires: pandas
Requires: xlrd
Requires-Dist: pandas
Requires-Dist: xlrd
Requires-Dist: requests
